{
  "total": 119,
  "success": 119,
  "failed": 0,
  "totalSongs": 9381,
  "timestamp": "2026-02-05T00:37:11.820Z",
  "artists": {
    "twice": {
      "displayName": "TWICE",
      "appleMusicId": "1203816887",
      "songCount": 229,
      "hasArtwork": true
    },
    "bts": {
      "displayName": "BTS",
      "appleMusicId": "883131348",
      "songCount": 156,
      "hasArtwork": true
    },
    "blackpink": {
      "displayName": "BLACKPINK",
      "appleMusicId": "1141774019",
      "songCount": 36,
      "hasArtwork": true
    },
    "le-sserafim": {
      "displayName": "LE SSERAFIM",
      "appleMusicId": "1616740364",
      "songCount": 43,
      "hasArtwork": true
    },
    "itzy": {
      "displayName": "ITZY",
      "appleMusicId": "1451964345",
      "songCount": 100,
      "hasArtwork": true
    },
    "aespa": {
      "displayName": "aespa",
      "appleMusicId": "1540251304",
      "songCount": 67,
      "hasArtwork": true
    },
    "newjeans": {
      "displayName": "NewJeans",
      "appleMusicId": "1635469693",
      "songCount": 21,
      "hasArtwork": true
    },
    "ive": {
      "displayName": "IVE",
      "appleMusicId": "1594159996",
      "songCount": 51,
      "hasArtwork": true
    },
    "i-dle": {
      "displayName": "i-dle",
      "appleMusicId": "1378887586",
      "songCount": 86,
      "hasArtwork": true
    },
    "red-velvet": {
      "displayName": "Red Velvet",
      "appleMusicId": "906961899",
      "songCount": 126,
      "hasArtwork": true
    },
    "dreamcatcher": {
      "displayName": "Dreamcatcher",
      "appleMusicId": "1194912387",
      "songCount": 86,
      "hasArtwork": true
    },
    "everglow": {
      "displayName": "EVERGLOW",
      "appleMusicId": "1456576473",
      "songCount": 31,
      "hasArtwork": true
    },
    "stayc": {
      "displayName": "STAYC",
      "appleMusicId": "1538881438",
      "songCount": 46,
      "hasArtwork": true
    },
    "kiss-of-life": {
      "displayName": "KISS OF LIFE",
      "appleMusicId": "1694672936",
      "songCount": 35,
      "hasArtwork": true
    },
    "katseye": {
      "displayName": "KATSEYE",
      "appleMusicId": "1754284416",
      "songCount": 14,
      "hasArtwork": true
    },
    "triples": {
      "displayName": "tripleS",
      "appleMusicId": "1651595986",
      "songCount": 87,
      "hasArtwork": true
    },
    "babymonster": {
      "displayName": "BABYMONSTER",
      "appleMusicId": "1715981813",
      "songCount": 20,
      "hasArtwork": true
    },
    "girls-generation": {
      "displayName": "Girls",
      "appleMusicId": "1014291",
      "songCount": 36,
      "hasArtwork": true
    },
    "mamamoo": {
      "displayName": "MAMAMOO",
      "appleMusicId": "818951094",
      "songCount": 121,
      "hasArtwork": true
    },
    "gfriend": {
      "displayName": "GFRIEND",
      "appleMusicId": "958416186",
      "songCount": 94,
      "hasArtwork": true
    },
    "xg": {
      "displayName": "XG",
      "appleMusicId": "1609409493",
      "songCount": 40,
      "hasArtwork": true
    },
    "ioi": {
      "displayName": "I.O.I",
      "appleMusicId": "1110816583",
      "songCount": 14,
      "hasArtwork": true
    },
    "aoa": {
      "displayName": "AOA",
      "appleMusicId": "1080563762",
      "songCount": 67,
      "hasArtwork": true
    },
    "chung-ha": {
      "displayName": "CHUNG HA",
      "appleMusicId": "1148527055",
      "songCount": 86,
      "hasArtwork": true
    },
    "fromis-9": {
      "displayName": "fromis_9",
      "appleMusicId": "1319150216",
      "songCount": 62,
      "hasArtwork": true
    },
    "wjsn": {
      "displayName": "WJSN",
      "appleMusicId": "1087651007",
      "songCount": 77,
      "hasArtwork": true
    },
    "loona": {
      "displayName": "LOONA",
      "appleMusicId": "1182243801",
      "songCount": 67,
      "hasArtwork": true
    },
    "weeekly": {
      "displayName": "Weeekly",
      "appleMusicId": "1519970666",
      "songCount": 43,
      "hasArtwork": true
    },
    "nmixx": {
      "displayName": "NMIXX",
      "appleMusicId": "1600411676",
      "songCount": 48,
      "hasArtwork": true
    },
    "kep1er": {
      "displayName": "Kep1er",
      "appleMusicId": "1594156263",
      "songCount": 59,
      "hasArtwork": true
    },
    "illit": {
      "displayName": "ILLIT",
      "appleMusicId": "1734551937",
      "songCount": 23,
      "hasArtwork": true
    },
    "tri-be": {
      "displayName": "TRI.BE",
      "appleMusicId": "1552829297",
      "songCount": 24,
      "hasArtwork": true
    },
    "h1-key": {
      "displayName": "H1-KEY",
      "appleMusicId": "1600832111",
      "songCount": 24,
      "hasArtwork": true
    },
    "billlie": {
      "displayName": "Billlie",
      "appleMusicId": "1594150790",
      "songCount": 44,
      "hasArtwork": true
    },
    "viviz": {
      "displayName": "VIVIZ",
      "appleMusicId": "1594151808",
      "songCount": 44,
      "hasArtwork": true
    },
    "kara": {
      "displayName": "KARA",
      "appleMusicId": "385160775",
      "songCount": 125,
      "hasArtwork": true
    },
    "clc": {
      "displayName": "CLC",
      "appleMusicId": "978594123",
      "songCount": 49,
      "hasArtwork": true
    },
    "momoland": {
      "displayName": "MOMOLAND",
      "appleMusicId": "1174745559",
      "songCount": 36,
      "hasArtwork": true
    },
    "exid": {
      "displayName": "EXID",
      "appleMusicId": "503473013",
      "songCount": 56,
      "hasArtwork": true
    },
    "oh-my-girl": {
      "displayName": "OH MY GIRL",
      "appleMusicId": "987326929",
      "songCount": 106,
      "hasArtwork": true
    },
    "apink": {
      "displayName": "Apink",
      "appleMusicId": "482854746",
      "songCount": 111,
      "hasArtwork": true
    },
    "sistar": {
      "displayName": "SISTAR",
      "appleMusicId": "380432623",
      "songCount": 55,
      "hasArtwork": true
    },
    "2ne1": {
      "displayName": "2NE1",
      "appleMusicId": "329155759",
      "songCount": 37,
      "hasArtwork": true
    },
    "wonder-girls": {
      "displayName": "Wonder Girls",
      "appleMusicId": "289029151",
      "songCount": 58,
      "hasArtwork": true
    },
    "miss-a": {
      "displayName": "miss A",
      "appleMusicId": "312076995",
      "songCount": 40,
      "hasArtwork": true
    },
    "fx": {
      "displayName": "f(x)",
      "appleMusicId": "425076892",
      "songCount": 58,
      "hasArtwork": true
    },
    "t-ara": {
      "displayName": "T-ara",
      "appleMusicId": "471900661",
      "songCount": 76,
      "hasArtwork": true
    },
    "secret": {
      "displayName": "Secret",
      "appleMusicId": "829418014",
      "songCount": 42,
      "hasArtwork": true
    },
    "4minute": {
      "displayName": "4minute",
      "appleMusicId": "371898647",
      "songCount": 69,
      "hasArtwork": true
    },
    "stray-kids": {
      "displayName": "Stray Kids",
      "appleMusicId": "1304823362",
      "songCount": 219,
      "hasArtwork": true
    },
    "seventeen": {
      "displayName": "SEVENTEEN",
      "appleMusicId": "999644772",
      "songCount": 170,
      "hasArtwork": true
    },
    "enhypen": {
      "displayName": "ENHYPEN",
      "appleMusicId": "1541011620",
      "songCount": 84,
      "hasArtwork": true
    },
    "tomorrow-x-together": {
      "displayName": "TXT",
      "appleMusicId": "1454642552",
      "songCount": 96,
      "hasArtwork": true
    },
    "ateez": {
      "displayName": "ATEEZ",
      "appleMusicId": "1439301205",
      "songCount": 140,
      "hasArtwork": true
    },
    "nct-127": {
      "displayName": "NCT 127",
      "appleMusicId": "1235849306",
      "songCount": 145,
      "hasArtwork": true
    },
    "nct-dream": {
      "displayName": "NCT DREAM",
      "appleMusicId": "1208839599",
      "songCount": 124,
      "hasArtwork": true
    },
    "nct-u": {
      "displayName": "NCT U",
      "appleMusicId": "1614202131",
      "songCount": 31,
      "hasArtwork": true
    },
    "exo": {
      "displayName": "EXO",
      "appleMusicId": "657630070",
      "songCount": 135,
      "hasArtwork": true
    },
    "bigbang": {
      "displayName": "BIGBANG",
      "appleMusicId": "318754656",
      "songCount": 104,
      "hasArtwork": true
    },
    "super-junior": {
      "displayName": "Super Junior",
      "appleMusicId": "284066214",
      "songCount": 229,
      "hasArtwork": true
    },
    "shinee": {
      "displayName": "SHINee",
      "appleMusicId": "433371033",
      "songCount": 201,
      "hasArtwork": true
    },
    "got7": {
      "displayName": "GOT7",
      "appleMusicId": "802694659",
      "songCount": 187,
      "hasArtwork": true
    },
    "monsta-x": {
      "displayName": "MONSTA X",
      "appleMusicId": "992315362",
      "songCount": 175,
      "hasArtwork": true
    },
    "nct": {
      "displayName": "NCT",
      "appleMusicId": "1533299115",
      "songCount": 189,
      "hasArtwork": true
    },
    "wayv": {
      "displayName": "WayV",
      "appleMusicId": "1449462311",
      "songCount": 81,
      "hasArtwork": true
    },
    "riize": {
      "displayName": "RIIZE",
      "appleMusicId": "1702435257",
      "songCount": 30,
      "hasArtwork": true
    },
    "treasure": {
      "displayName": "TREASURE",
      "appleMusicId": "1526319335",
      "songCount": 43,
      "hasArtwork": true
    },
    "the-boyz": {
      "displayName": "THE BOYZ",
      "appleMusicId": "1322012460",
      "songCount": 159,
      "hasArtwork": true
    },
    "ikon": {
      "displayName": "iKON",
      "appleMusicId": "1044506362",
      "songCount": 76,
      "hasArtwork": true
    },
    "winner": {
      "displayName": "WINNER",
      "appleMusicId": "908222845",
      "songCount": 62,
      "hasArtwork": true
    },
    "day6": {
      "displayName": "DAY6",
      "appleMusicId": "1037939997",
      "songCount": 125,
      "hasArtwork": true
    },
    "pentagon": {
      "displayName": "PENTAGON",
      "appleMusicId": "1346387122",
      "songCount": 109,
      "hasArtwork": true
    },
    "sf9": {
      "displayName": "SF9",
      "appleMusicId": "1161961912",
      "songCount": 110,
      "hasArtwork": true
    },
    "oneus": {
      "displayName": "ONEUS",
      "appleMusicId": "1437510375",
      "songCount": 93,
      "hasArtwork": true
    },
    "onewe": {
      "displayName": "ONEWE",
      "appleMusicId": "1437510372",
      "songCount": 67,
      "hasArtwork": true
    },
    "verivery": {
      "displayName": "VERIVERY",
      "appleMusicId": "1436821750",
      "songCount": 55,
      "hasArtwork": true
    },
    "cravity": {
      "displayName": "CRAVITY",
      "appleMusicId": "1507226584",
      "songCount": 90,
      "hasArtwork": true
    },
    "p1harmony": {
      "displayName": "P1Harmony",
      "appleMusicId": "1536862708",
      "songCount": 61,
      "hasArtwork": true
    },
    "kard": {
      "displayName": "KARD",
      "appleMusicId": "1215832588",
      "songCount": 47,
      "hasArtwork": true
    },
    "astro": {
      "displayName": "ASTRO",
      "appleMusicId": "1086927524",
      "songCount": 93,
      "hasArtwork": true
    },
    "victon": {
      "displayName": "VICTON",
      "appleMusicId": "1065470220",
      "songCount": 61,
      "hasArtwork": true
    },
    "ab6ix": {
      "displayName": "AB6IX",
      "appleMusicId": "1463405847",
      "songCount": 107,
      "hasArtwork": true
    },
    "cix": {
      "displayName": "CIX",
      "appleMusicId": "1473471758",
      "songCount": 59,
      "hasArtwork": true
    },
    "to1": {
      "displayName": "TO1",
      "appleMusicId": "1567861660",
      "songCount": 25,
      "hasArtwork": true
    },
    "tempest": {
      "displayName": "TEMPEST",
      "appleMusicId": "1611097082",
      "songCount": 44,
      "hasArtwork": true
    },
    "omega-x": {
      "displayName": "OMEGA X",
      "appleMusicId": "1574080700",
      "songCount": 44,
      "hasArtwork": true
    },
    "xikers": {
      "displayName": "xikers",
      "appleMusicId": "1678885244",
      "songCount": 39,
      "hasArtwork": true
    },
    "zerobaseone": {
      "displayName": "ZEROBASEONE",
      "appleMusicId": "1693315406",
      "songCount": 49,
      "hasArtwork": true
    },
    "boynextdoor": {
      "displayName": "BOYNEXTDOOR",
      "appleMusicId": "1687612559",
      "songCount": 35,
      "hasArtwork": true
    },
    "tws": {
      "displayName": "TWS",
      "appleMusicId": "1721226191",
      "songCount": 30,
      "hasArtwork": true
    },
    "btob": {
      "displayName": "BTOB",
      "appleMusicId": "515372357",
      "songCount": 153,
      "hasArtwork": true
    },
    "highlight": {
      "displayName": "Highlight",
      "appleMusicId": "1221833558",
      "songCount": 48,
      "hasArtwork": true
    },
    "infinite": {
      "displayName": "INFINITE",
      "appleMusicId": "407674485",
      "songCount": 107,
      "hasArtwork": true
    },
    "vixx": {
      "displayName": "VIXX",
      "appleMusicId": "531227182",
      "songCount": 102,
      "hasArtwork": true
    },
    "block-b": {
      "displayName": "Block B",
      "appleMusicId": "673862599",
      "songCount": 51,
      "hasArtwork": true
    },
    "b1a4": {
      "displayName": "B1A4",
      "appleMusicId": "433573050",
      "songCount": 150,
      "hasArtwork": true
    },
    "teen-top": {
      "displayName": "TEEN TOP",
      "appleMusicId": "415785922",
      "songCount": 96,
      "hasArtwork": true
    },
    "myname": {
      "displayName": "MYNAME",
      "appleMusicId": "530052009",
      "songCount": 107,
      "hasArtwork": true
    },
    "nu-est": {
      "displayName": "NU",
      "appleMusicId": "214324493",
      "songCount": 52,
      "hasArtwork": true
    },
    "boyfriend": {
      "displayName": "Boyfriend",
      "appleMusicId": "1729240738",
      "songCount": 0,
      "hasArtwork": true
    },
    "ukiss": {
      "displayName": "U-KISS",
      "appleMusicId": "410587085",
      "songCount": 169,
      "hasArtwork": true
    },
    "iu": {
      "displayName": "IU",
      "appleMusicId": "409076743",
      "songCount": 135,
      "hasArtwork": true
    },
    "taeyeon": {
      "displayName": "Taeyeon",
      "appleMusicId": "435966642",
      "songCount": 121,
      "hasArtwork": true
    },
    "sunmi": {
      "displayName": "Sunmi",
      "appleMusicId": "693899983",
      "songCount": 52,
      "hasArtwork": true
    },
    "hyuna": {
      "displayName": "HyunA",
      "appleMusicId": "384855556",
      "songCount": 49,
      "hasArtwork": true
    },
    "jessi": {
      "displayName": "Jessi",
      "appleMusicId": "911707693",
      "songCount": 46,
      "hasArtwork": true
    },
    "jeon-somi": {
      "displayName": "SOMI",
      "appleMusicId": "218606475",
      "songCount": 59,
      "hasArtwork": true
    },
    "yuqi": {
      "displayName": "Yuqi",
      "appleMusicId": "1566541268",
      "songCount": 20,
      "hasArtwork": true
    },
    "kwon-eunbi": {
      "displayName": "Kwon Eunbi",
      "appleMusicId": "1450362751",
      "songCount": 38,
      "hasArtwork": true
    },
    "baekhyun": {
      "displayName": "Baekhyun",
      "appleMusicId": "987357639",
      "songCount": 55,
      "hasArtwork": true
    },
    "kai": {
      "displayName": "KAI",
      "appleMusicId": "1508288900",
      "songCount": 25,
      "hasArtwork": true
    },
    "taemin": {
      "displayName": "Taemin",
      "appleMusicId": "971826499",
      "songCount": 95,
      "hasArtwork": true
    },
    "g-dragon": {
      "displayName": "G-Dragon",
      "appleMusicId": "320373708",
      "songCount": 52,
      "hasArtwork": true
    },
    "taeyang": {
      "displayName": "Taeyang",
      "appleMusicId": "1683284485",
      "songCount": 46,
      "hasArtwork": true
    },
    "jay-park": {
      "displayName": "Jay Park",
      "appleMusicId": "384641776",
      "songCount": 196,
      "hasArtwork": true
    },
    "dean": {
      "displayName": "DEAN",
      "appleMusicId": "2770824",
      "songCount": 27,
      "hasArtwork": true
    },
    "crush": {
      "displayName": "Crush",
      "appleMusicId": "958641367",
      "songCount": 117,
      "hasArtwork": true
    },
    "zico": {
      "displayName": "Zico",
      "appleMusicId": "656726368",
      "songCount": 52,
      "hasArtwork": true
    },
    "kpop-demon-hunters": {
      "displayName": "Kpop Demon Hunters",
      "appleMusicId": "1820264140",
      "songCount": 13,
      "hasArtwork": true
    }
  }
}